{
    "empty_email": "Enter Email address",
    "valid_email":"Enter The valid Email",
    "alerdy_email":"Email Already Exists ",
    "empty_first_name":"Enter First name",
    "empty_last_name":"Enter Last name",
    "empty_password":"Enter Password",
    "password_length_6": "Password must be minimum 6 character long",
    "empty_role":"Enter The Role",
    "valid_role":"Please provide a valid role",
    "registration_success":"User registered successfully",
    "something_went_wrong": "Something went wrong",
    "invalid_email":"Invalid Email",
    "invalid_password":"Invalid Password",
    "login_success":"User login successfully",
    "invalid_token":"Invalid Token",
    "getUser":"User Profile",
    "getUSerAll":"All User Data",
    "userUpdate":"User details updated successfully",
    "userDelete":"User Delete successfully",
    "invalid_phone":"Enter The 10 Digit Mobile Number",
    "profileUpdate": "Profile updated successfully.",
    "no_token_provided": "No token provided.",
    "user_not_found": "User not found.",
    "unauthorized_role": "You are not authorized to update these fields.",
    "Search_User":"successfully Search User",
    "admin_craeted_event":"Only Admin Created",
    "empty_event_date":"Enter The Event Date",
    "empty_event_name":"Enter The Event Name",
    "empty_event_des":"Enter The Event Description",
    "event_success":"Event Craeted successfully",
    "event_not_found":"Event Not Found",
    "eventDeletd":"successfully Event Deleted",
    "display_Event":"Display All Events",
    "empty_leave_Date":"Enter The Leave Date",
    "reason_name":"Enter The Reason Name",
    "reason_des":"Enter The Reason Description",
    "leave_created":"successfully Leave Created",
    "leave_not_found":"Leave not found",
    "leave_update":"successfully leave update",
    "mention":"Enter The mention",
    "empty_check_in":"Enter The Check in Time",
    "valid_check_in":"Check-in time must be between 01:00 and 24:00 in HH:mm format.",
    "empty_check_out":"Enter The Check out time",
    "valid_check_out":"Check-out time must be between 01:00 and 24:00 in HH:mm format.",
    "valid_break_start":"Break start time must be between 01:00 and 24:00 in HH:mm format.",
    "valid_break_out":"Break stop time must be between 01:00 and 24:00 in HH:mm format.",
    "attdance_craeted":"successfully attdance created"
}